py_mmtx_client/__init__.py
py_mmtx_client/client/api_base.py
py_mmtx_client/client/api_config_client.py
py_mmtx_client/client/api_hls_client.py
py_mmtx_client/client/api_path_client.py
py_mmtx_client/config.py
py_mmtx_client/models/base_models.py
py_mmtx_client/models/config_models.py
py_mmtx_client/models/hls_models.py
py_mmtx_client/models/path_models.py
py_mmtx_client/tools.py
py_mmtx_client-0.2.0.dist-info/METADATA
py_mmtx_client-0.2.0.dist-info/WHEEL
py_mmtx_client-0.2.0.dist-info/RECORD
